{"walls":[{"position":{"x":5.53,"y":-0.65,"z":-0.323459119},"rotation":{"X":0.0,"Y":0.0,"Z":-0.9776492,"W":0.210242718},"size":{"x":1.69899964,"y":11.7379961,"z":1.0}},{"position":{"x":-5.1,"y":0.02,"z":-0.323459119},"rotation":{"X":0.0,"Y":0.0,"Z":-0.2493699,"W":0.968408346},"size":{"x":1.699,"y":11.737999,"z":1.0}},{"position":{"x":-0.28,"y":5.33,"z":-0.323459119},"rotation":{"X":0.0,"Y":0.0,"Z":-0.696907759,"W":0.7171608},"size":{"x":1.699,"y":11.737999,"z":1.0}},{"position":{"x":2.64,"y":-5.89,"z":-0.323459119},"rotation":{"X":0.0,"Y":0.0,"Z":-0.9776492,"W":0.210242718},"size":{"x":1.69899964,"y":11.7379961,"z":1.0}},{"position":{"x":-3.15,"y":-5.64,"z":-0.323459119},"rotation":{"X":0.0,"Y":0.0,"Z":-0.2493699,"W":0.968408346},"size":{"x":1.699,"y":11.737999,"z":1.0}}],"towerPosition":[{"x":-0.02529335,"y":0.5459652,"z":-0.323459119}],"player":{"position":{"x":-6.23,"y":-6.26,"z":0.0},"rotation":{"X":0.0,"Y":0.0,"Z":0.953717,"W":0.30070582}},"endAt":{"x":5.29,"y":-6.24,"z":0.0}}